[
  {
    "title": "gold-sponsors",
    "logos": [
      {
        "name": "Google",
        "url": "//www.google.com.ua/intl/en/about/",
        "logoUrl": "../images/logos/google.svg",
        "width": 170
      },
      {
        "name": "GDG Fresno",
        "url": "//www.meetup.com/googledevelopers/",
        "logoUrl": "../images/logos/GDG_Fresno.svg",
        "width": 170
      },
      {
        "name": "Fresno City College",
        "url": "//fresnocitycollege.edu/",
        "logoUrl": "../images/logos/fcc_logo_wordmark.png",
        "width": 170
      }
    ]
  },
  {
    "title": "general-partner",
    "logos": [
      {
        "name": "GDG Visalia",
        "url": "//www.meetup.com/GDG-Visalia-Google-Developer-Group/",
        "logoUrl": "../images/logos/GDG_Visalia.svg"
      },
      {
        "name": "GDG Oakdale",
        "url": "//www.meetup.com/GDG-Oakdale/",
        "logoUrl": "../images/logos/GDG_Oakdale.svg"
      },
      {
        "name": "GDG Modesto",
        "url": "//www.meetup.com/GDG-Modesto-Google-Developer-Group/",
        "logoUrl": "../images/logos/GDG_Modesto.svg"
      },
      {
        "name": "Bitwise",
        "url": "//bitwiseindustries.com/",
        "logoUrl": "../images/logos/bitwise.png"
      },
      {
        "name": "Fresno Ideaworks",
        "url": "//fresnoideaworks.org/",
        "logoUrl": "../images/logos/ideaworks-logo-invert.png"
      }
    ]
  }
]
